MANIFEST.in
README.rst
setup.py
django_extramimetypes.egg-info/PKG-INFO
django_extramimetypes.egg-info/SOURCES.txt
django_extramimetypes.egg-info/dependency_links.txt
django_extramimetypes.egg-info/requires.txt
django_extramimetypes.egg-info/top_level.txt
extramimetypes/__init__.py
tests/__init__.py