Metadata-Version: 1.0
Name: django-extramimetypes
Version: 0.1.0
Summary: Hooks into Python's mimetypes module to allow extra mimetype guesses to be defined.
Home-page: https://github.com/bradleyayers/django-extramimetypes/
Author: Bradley Ayers
Author-email: bradley.ayers@gmail.com
License: UNKNOWN
Platform: UNKNOWN
Classifier: Environment :: Web Environment
Classifier: Framework :: Django
Classifier: Intended Audience :: Developers
Classifier: Operating System :: OS Independent
Classifier: Programming Language :: Python
Classifier: Topic :: Internet :: WWW/HTTP
Classifier: Topic :: Internet :: WWW/HTTP :: Dynamic Content
Classifier: Topic :: Software Development :: Libraries :: Python Modules
